leekoq/__init__.py
leekoq/leekoq.py
leekoq-1.0.dist-info/LICENSE
leekoq-1.0.dist-info/METADATA
leekoq-1.0.dist-info/WHEEL
leekoq-1.0.dist-info/top_level.txt
leekoq-1.0.dist-info/RECORD
