Metadata-Version: 2.1
Name: leekoq
Version: 1.0
Summary: Python implementation of Keeloq encryption algorithm
Home-page: https://github.com/socram8888/leekoq
Author: Marcos Del Sol Vives
Author-email: marcos@orca.pet
License: WTFPL
Project-URL: Bug Tracker, https://github.com/socram8888/leekoq/issues
Project-URL: Source Code, https://github.com/socram8888/leekoq
Keywords: keeloq microchip code-hopping rolling-code
Platform: UNKNOWN
Classifier: Topic :: Security
Classifier: Topic :: Security :: Cryptography
Classifier: License :: Freely Distributable
